facecam/__init__.py
facecam/resources/.DS_Store
facecam/resources/opencv_face_detector.pbtxt
facecam/resources/opencv_face_detector_uint8.pb
facecam/resources/img/.DS_Store
facecam/resources/img/band.png
facecam/resources/img/beard.png
facecam/resources/img/cat.png
facecam/resources/img/flower.png
facecam/resources/img/glass_1.png
facecam/resources/img/glass_2.png
facecam/resources/img/hat.png
facecam/resources/img/heart.png
facecam/resources/img/mask_1.png
facecam/resources/img/mask_2.png
facecam/resources/img/mouth_1.png
facecam/resources/img/mouth_2.png
facecam/resources/img/nose.png
facecam/resources/img/rabbit.png
facecam/resources/img/tie.png
facecam/resources/img/tiger.png
facecam-0.0.1a0.dist-info/METADATA
facecam-0.0.1a0.dist-info/WHEEL
facecam-0.0.1a0.dist-info/top_level.txt
facecam-0.0.1a0.dist-info/RECORD
